setup.py
frame_msgs/__init__.py
frame_msgs/msg/_DetectedPerson.py
frame_msgs/msg/_DetectedPersons.py
frame_msgs/msg/_PersonTrajectories.py
frame_msgs/msg/_PersonTrajectory.py
frame_msgs/msg/_PersonTrajectoryEntry.py
frame_msgs/msg/_TrackedPerson.py
frame_msgs/msg/_TrackedPerson2d.py
frame_msgs/msg/_TrackedPersons.py
frame_msgs/msg/_TrackedPersons2d.py
frame_msgs/msg/__init__.py
ros_frame_msgs.egg-info/PKG-INFO
ros_frame_msgs.egg-info/SOURCES.txt
ros_frame_msgs.egg-info/dependency_links.txt
ros_frame_msgs.egg-info/top_level.txt
spencer_tracking_msgs/__init__.py
spencer_tracking_msgs/msg/_CompositeDetectedPerson.py
spencer_tracking_msgs/msg/_CompositeDetectedPersons.py
spencer_tracking_msgs/msg/_DetectedPerson.py
spencer_tracking_msgs/msg/_DetectedPersons.py
spencer_tracking_msgs/msg/_ImmDebugInfo.py
spencer_tracking_msgs/msg/_ImmDebugInfos.py
spencer_tracking_msgs/msg/_TrackedGroup.py
spencer_tracking_msgs/msg/_TrackedGroups.py
spencer_tracking_msgs/msg/_TrackedPerson.py
spencer_tracking_msgs/msg/_TrackedPerson2d.py
spencer_tracking_msgs/msg/_TrackedPersons.py
spencer_tracking_msgs/msg/_TrackedPersons2d.py
spencer_tracking_msgs/msg/_TrackingTimingMetrics.py
spencer_tracking_msgs/msg/__init__.py
spencer_tracking_msgs/srv/_GetPersonTrajectories.py
spencer_tracking_msgs/srv/__init__.py