Metadata-Version: 1.0
Name: ros-frame-msgs
Version: 0.0.2
Summary: frame_msgs package from ROS, in pip form
Home-page: UNKNOWN
Author: Daniel Dugas
Author-email: UNKNOWN
License: UNKNOWN
Platform: UNKNOWN
